CHANGES.rst
CONTRIBUTORS.rst
LICENSE.rst
MANIFEST.in
README.rst
pyproject.toml
setup.py
docs/conf.py
docs/index.md
src/urban/__init__.py
src/urban.schedule.egg-info/PKG-INFO
src/urban.schedule.egg-info/SOURCES.txt
src/urban.schedule.egg-info/dependency_links.txt
src/urban.schedule.egg-info/entry_points.txt
src/urban.schedule.egg-info/namespace_packages.txt
src/urban.schedule.egg-info/not-zip-safe
src/urban.schedule.egg-info/requires.txt
src/urban.schedule.egg-info/top_level.txt
src/urban/schedule/__init__.py
src/urban/schedule/configure.zcml
src/urban/schedule/interfaces.py
src/urban/schedule/permissions.zcml
src/urban/schedule/setuphandlers.py
src/urban/schedule/testing.py
src/urban/schedule/upgrades.py
src/urban/schedule/upgrades.zcml
src/urban/schedule/utils.py
src/urban/schedule/browser/__init__.py
src/urban/schedule/browser/configure.zcml
src/urban/schedule/browser/overrides/.gitkeep
src/urban/schedule/browser/static/.gitkeep
src/urban/schedule/conditions/__init__.py
src/urban/schedule/conditions/configure.zcml
src/urban/schedule/conditions/creation.py
src/urban/schedule/conditions/ending.py
src/urban/schedule/conditions/start_date.py
src/urban/schedule/locales/README.rst
src/urban/schedule/locales/__init__.py
src/urban/schedule/locales/imio.schedule.pot
src/urban/schedule/locales/update.py
src/urban/schedule/locales/update.sh
src/urban/schedule/locales/urban.schedule.pot
src/urban/schedule/locales/en/LC_MESSAGES/imio.schedule.mo
src/urban/schedule/locales/en/LC_MESSAGES/imio.schedule.po
src/urban/schedule/locales/en/LC_MESSAGES/urban.schedule.mo
src/urban/schedule/locales/en/LC_MESSAGES/urban.schedule.po
src/urban/schedule/locales/fr/LC_MESSAGES/imio.schedule.mo
src/urban/schedule/locales/fr/LC_MESSAGES/imio.schedule.po
src/urban/schedule/locales/fr/LC_MESSAGES/urban.schedule.mo
src/urban/schedule/locales/fr/LC_MESSAGES/urban.schedule.po
src/urban/schedule/profiles/config/liege/codt_buildlicence/attente_plans_modifies.json
src/urban/schedule/profiles/config/liege/codt_buildlicence/avis-fd.json
src/urban/schedule/profiles/config/liege/codt_buildlicence/verif_complet.json
src/urban/schedule/profiles/config/liege/codt_urbancertificatetwo/verif_complet.json
src/urban/schedule/profiles/config/liege/roaddecree/decision-notification.json
